LICENSE
README.md
lyykline_tk.py
setup.py
lyykline_tk.egg-info/PKG-INFO
lyykline_tk.egg-info/SOURCES.txt
lyykline_tk.egg-info/dependency_links.txt
lyykline_tk.egg-info/top_level.txt