Metadata-Version: 2.1
Name: lyykline_tk
Version: 1.1
Summary: lyykline for lyy
Author: lyy
Author-email: 
License: MIT
License-File: LICENSE
